{
  "type": "ContractingTriangleWave",
  "points": [
    {
      "time_offset": 0,
      "price": 118
    },
    {
      "time_offset": 6,
      "price": 103
    },
    {
      "time_offset": 9,
      "price": 113
    },
    {
      "time_offset": 12,
      "price": 106
    },
    {
      "time_offset": 14,
      "price": 112
    },
    {
      "time_offset": 19,
      "price": 108
    }
  ],
  "sub_wave": [
    {
      "type": "ZigZagCombinationWave",
      "points": [],
      "sub_wave": []
    },
    {
      "type": "ZigZagWave",
      "points": [],
      "sub_wave": []
    },
    {
      "type": "ZigZagWave",
      "points": [],
      "sub_wave": []
    },
    {
      "type": "ZigZagWave",
      "points": [],
      "sub_wave": []
    },
    {
      "type": "ZigZagWave",
      "points": [],
      "sub_wave": []
    }
  ]
}